vaine/__init__.py
vaine/_version.py
vaine/example.py
vaine/natural_experiment.py
vaine/react_jupyter_widget.py
vaine/util.py
vaine/static/extension.js
vaine/static/index.js
vaine/static/index.js.map
vaine_widget-0.1.0a0.data/data/etc/jupyter/nbconfig/notebook.d/vaine-widget.json
vaine_widget-0.1.0a0.data/data/share/jupyter/nbextensions/vaine-widget/extension.js
vaine_widget-0.1.0a0.data/data/share/jupyter/nbextensions/vaine-widget/index.js
vaine_widget-0.1.0a0.data/data/share/jupyter/nbextensions/vaine-widget/index.js.map
vaine_widget-0.1.0a0.dist-info/METADATA
vaine_widget-0.1.0a0.dist-info/WHEEL
vaine_widget-0.1.0a0.dist-info/top_level.txt
vaine_widget-0.1.0a0.dist-info/RECORD
